ArabicNames
